LICENSE.txt
MANIFEST.in
README.rst
setup.py
reflowrst/__init__.py
reflowrst/collect_bullet_list_item.py
reflowrst/collect_citation.py
reflowrst/collect_directive.py
reflowrst/collect_enumerated_list_item.py
reflowrst/collect_field.py
reflowrst/collect_footnote.py
reflowrst/collect_gridtable.py
reflowrst/collect_line_block.py
reflowrst/collect_literal_block.py
reflowrst/collect_main_title.py
reflowrst/collect_option_list_item.py
reflowrst/collect_paragraph.py
reflowrst/collect_simple_table.py
reflowrst/collect_title.py
reflowrst/is_bullet_list_item.py
reflowrst/is_citation.py
reflowrst/is_definition_term.py
reflowrst/is_directive.py
reflowrst/is_enumerated_list_item.py
reflowrst/is_field.py
reflowrst/is_footnote.py
reflowrst/is_gridtable.py
reflowrst/is_line_block.py
reflowrst/is_literal_block.py
reflowrst/is_main_title.py
reflowrst/is_option_list_item.py
reflowrst/is_simple_table.py
reflowrst/is_title.py
reflowrst/is_transition.py
reflowrst/reflow.py
reflowrst/reflow_bullet_list_item.py
reflowrst/reflow_citation.py
reflowrst/reflow_enumerated_list_item.py
reflowrst/reflow_field.py
reflowrst/reflow_footnote.py
reflowrst/reflow_option_list_item.py
reflowrst/reflow_paragraph.py
reflowrst.egg-info/PKG-INFO
reflowrst.egg-info/SOURCES.txt
reflowrst.egg-info/dependency_links.txt
reflowrst.egg-info/requires.txt
reflowrst.egg-info/top_level.txt
reflowrst/__pycache__/__init__.cpython-36.pyc
reflowrst/__pycache__/collect_bullet_list_item.cpython-36.pyc
reflowrst/__pycache__/collect_citation.cpython-36.pyc
reflowrst/__pycache__/collect_directive.cpython-36.pyc
reflowrst/__pycache__/collect_enumerated_list_item.cpython-36.pyc
reflowrst/__pycache__/collect_field.cpython-36.pyc
reflowrst/__pycache__/collect_footnote.cpython-36.pyc
reflowrst/__pycache__/collect_gridtable.cpython-36.pyc
reflowrst/__pycache__/collect_line_block.cpython-36.pyc
reflowrst/__pycache__/collect_literal_block.cpython-36.pyc
reflowrst/__pycache__/collect_main_title.cpython-36.pyc
reflowrst/__pycache__/collect_option_list_item.cpython-36.pyc
reflowrst/__pycache__/collect_paragraph.cpython-36.pyc
reflowrst/__pycache__/collect_simple_table.cpython-36.pyc
