Metadata-Version: 1.1
Name: reflowrst
Version: 1.1.0
Summary: Modify valid rst text to fit within given width
Home-page: https://github.com/doakey3/reflowrst
Author: doakey3
Author-email: reflowrst.dmodo@spamgourmet.com
License: MIT
Download-URL: https://github.com/doakey3/reflowrst/tarball/1.1.0
Platform: UNKNOWN
